ObserverAPI/__init__.py
ObserverAPI/client.py
ObserverAPI/exception.py
ObserverAPI/observer.py
ObserverAPI/requests.py
ObserverAPI/utils.py
ObserverAPI/objects/__init__.py
ObserverAPI/objects/api.py
ObserverAPI/objects/leaderboards.py
ObserverAPI/objects/player.py
ObserverAPI/objects/ranking.py
ObserverAPI-1.1.5.dist-info/METADATA
ObserverAPI-1.1.5.dist-info/WHEEL
ObserverAPI-1.1.5.dist-info/top_level.txt
ObserverAPI-1.1.5.dist-info/RECORD
