Metadata-Version: 2.1
Name: ObserverAPI
Version: 1.1.5
Summary: Observer API Wrapper in Python
Home-page: https://github.com/Polsulpicien/ObserverAPI
Author: Polsulpicien
License: MIT
Project-URL: Documentation, https://github.com/Polsulpicien/ObserverAPI/blob/main/docs/docs.md
Project-URL: Issue tracker, https://github.com/Polsulpicien/ObserverAPI/issues
Project-URL: Support, https://discord.com/invite/xm9QX3Q
Keywords: ObserverAPI
Platform: UNKNOWN
Classifier: Programming Language :: Python :: 3
Classifier: License :: OSI Approved :: MIT License
Classifier: Operating System :: OS Independent
Requires-Python: >=3.8
